aseriouspackage/.key.txt
aseriouspackage/.puzzle.txt
aseriouspackage/__init__.py
aseriouspackage/example.py
aseriouspackage/init.py
aseriouspackage-0.0.2.dist-info/METADATA
aseriouspackage-0.0.2.dist-info/WHEEL
aseriouspackage-0.0.2.dist-info/licenses/LICENSE
aseriouspackage-0.0.2.dist-info/RECORD
