Metadata-Version: 2.1
Name: aseriouspackage
Version: 0.0.2
Summary: A serious package for exam projects
Project-URL: Homepage, https://github.com/DYYDMC/aseriouspackage
Project-URL: Bug Tracker, https://github.com/DYYDMC/aseriouspackage/issues
Author-email: Jane Deng <yuyao.deng@uni-tuebingen.de>
License-File: LICENSE
Classifier: License :: OSI Approved :: MIT License
Classifier: Operating System :: OS Independent
Classifier: Programming Language :: Python :: 3
Requires-Python: >=3.6.8
